.long-description.html
README.rst
setup.py
src/collective/__init__.py
src/collective.cart.shipping.egg-info/PKG-INFO
src/collective.cart.shipping.egg-info/SOURCES.txt
src/collective.cart.shipping.egg-info/dependency_links.txt
src/collective.cart.shipping.egg-info/entry_points.txt
src/collective.cart.shipping.egg-info/namespace_packages.txt
src/collective.cart.shipping.egg-info/not-zip-safe
src/collective.cart.shipping.egg-info/requires.txt
src/collective.cart.shipping.egg-info/top_level.txt
src/collective/cart/__init__.py
src/collective/cart/shipping/__init__.py
src/collective/cart/shipping/configure.zcml
src/collective/cart/shipping/interfaces.py
src/collective/cart/shipping/schema.py
src/collective/cart/shipping/setuphandlers.py
src/collective/cart/shipping/upgrades.py
src/collective/cart/shipping/upgrades.zcml
src/collective/cart/shipping/vocabulary.py
src/collective/cart/shipping/Extensions/Install.py
src/collective/cart/shipping/Extensions/__init__.py
src/collective/cart/shipping/browser/__init__.py
src/collective/cart/shipping/browser/configure.zcml
src/collective/cart/shipping/browser/interfaces.py
src/collective/cart/shipping/browser/template.py
src/collective/cart/shipping/browser/static/shipping.png
src/collective/cart/shipping/browser/templates/shipping-method.pt
src/collective/cart/shipping/content/__init__.py
src/collective/cart/shipping/content/configure.zcml
src/collective/cart/shipping/content/shipping.py
src/collective/cart/shipping/docs/CONTRIBUTORS.rst
src/collective/cart/shipping/docs/CREDITS.rst
src/collective/cart/shipping/docs/HISTORY.rst
src/collective/cart/shipping/docs/INSTALL.rst
src/collective/cart/shipping/docs/LICENSE.rst
src/collective/cart/shipping/locales/collective.cart.shipping.pot
src/collective/cart/shipping/locales/fi/LC_MESSAGES/collective.cart.shipping.mo
src/collective/cart/shipping/locales/fi/LC_MESSAGES/collective.cart.shipping.po
src/collective/cart/shipping/profiles/default/browserlayer.xml
src/collective/cart/shipping/profiles/default/catalog.xml
src/collective/cart/shipping/profiles/default/collective.cart.shipping_various.txt
src/collective/cart/shipping/profiles/default/factorytool.xml
src/collective/cart/shipping/profiles/default/import_steps.xml
src/collective/cart/shipping/profiles/default/metadata.xml
src/collective/cart/shipping/profiles/default/propertiestool.xml
src/collective/cart/shipping/profiles/default/registry.xml
