Metadata-Version: 1.1
Name: collective.cart.shipping
Version: 0.7
Summary: Adds shipping methods to Plone.
Home-page: https://github.com/collective/collective.cart.shipping
Author: Taito Horiuchi
Author-email: taito.horiuchi@gmail.com
License: BSD
Platform: UNKNOWN
Classifier: Framework :: Plone
Classifier: Framework :: Plone :: 4.3
Classifier: License :: OSI Approved :: BSD License
Classifier: Programming Language :: Python
Classifier: Programming Language :: Python :: 2.7
